xmltv_alt.py
python_xmltvalt-1.5.1.dist-info/COPYING
python_xmltvalt-1.5.1.dist-info/METADATA
python_xmltvalt-1.5.1.dist-info/WHEEL
python_xmltvalt-1.5.1.dist-info/top_level.txt
python_xmltvalt-1.5.1.dist-info/RECORD
