Metadata-Version: 2.1
Name: python-xmltvalt
Version: 1.5.1
Summary: A Python Module for Reading and Writing XMLTV Files
Home-page: https://github.com/justinhorner/python-xmltv-alt
Author: Justin Horner, James Oakley
Author-email: mail@justinhorner.me, jfunk@funktronics.ca
License: LGPL-3.0+
Classifier: Development Status :: 4 - Beta
Classifier: Intended Audience :: Developers
Classifier: License :: OSI Approved :: GNU Library or Lesser General Public License (LGPL)
Classifier: Operating System :: OS Independent
Classifier: Programming Language :: Python :: 3
Classifier: Topic :: Software Development :: Libraries :: Python Modules
License-File: COPYING
